{"thumbnail":"images\/amethyst.jpg","theme":"Precious Stones","themeSound":"sounds\/precious_stones.mp3","words":[{"word":"amethyst","image":"images\/amethyst.jpg","sound":"sounds\/amethyst.mp3"},{"word":"aquamarine","image":"images\/aquamarine.jpg","sound":"sounds\/aquamarine.mp3"},{"word":"diamond","image":"images\/diamond.jpg","sound":"sounds\/diamond.mp3"},{"word":"emerald","image":"images\/emerald.jpg","sound":"sounds\/emerald.mp3"},{"word":"gold","image":"images\/gold.jpg","sound":"sounds\/gold.mp3"},{"word":"jade","image":"images\/jade.jpg","sound":"sounds\/jade.mp3"},{"word":"pearl","image":"images\/pearl.jpg","sound":"sounds\/pearl.mp3"},{"word":"quartz","image":"images\/quartz.jpg","sound":"sounds\/quartz.mp3"},{"word":"ruby","image":"images\/ruby.jpg","sound":"sounds\/ruby.mp3"},{"word":"sapphire","image":"images\/sapphire.jpg","sound":"sounds\/sapphire.mp3"},{"word":"silver","image":"images\/silver.jpg","sound":"sounds\/silver.mp3"},{"word":"topaz","image":"images\/topaz.jpg","sound":"sounds\/topaz.mp3"}],"quizeInfo":[{"type":1,"count":12},{"type":2,"count":4},{"type":3,"count":4}],"version":1,"id":56}