{"thumbnail":"images\/thumbnail.png","theme":"Famous Cities","words":[{"word":"Athens","image":"images\/Athens.jpg","sound":"sounds\/Athens.mp3"},{"word":"Cairo","image":"images\/Cairo.jpg","sound":"sounds\/Cairo.mp3"},{"word":"Istanbul","image":"images\/Istanbul.jpg","sound":"sounds\/Istanbul.mp3"},{"word":"Jerusalem","image":"images\/Jerusalem.jpg","sound":"sounds\/Jerusalem.mp3"},{"word":"London","image":"images\/London.jpg","sound":"sounds\/London.mp3"},{"word":"Moscow","image":"images\/Moscow.jpg","sound":"sounds\/Moscow.mp3"},{"word":"New York","image":"images\/New_York.jpg","sound":"sounds\/New_York.mp3"},{"word":"Paris","image":"images\/Paris.jpg","sound":"sounds\/Paris.mp3"},{"word":"Rio de Janeiro","image":"images\/Rio_de_Janeiro.jpg","sound":"sounds\/Rio_de_Janeiro.mp3"},{"word":"Rome","image":"images\/Rome.jpg","sound":"sounds\/Rome.mp3"},{"word":"San Francisco","image":"images\/San_Francisco.jpg","sound":"sounds\/San_Francisco.mp3"},{"word":"Sydney","image":"images\/Sydney.jpg","sound":"sounds\/Sydney.mp3"}],"quizeInfo":[{"type":1,"count":12},{"type":2,"count":3},{"type":3,"count":0}],"version":2,"id":"10","module":"2"}